{
  "dragon_grumble_1": {
    "subtitle": "Dragon grumbles",
    "sounds": [
      {
        "name": "lightningdragon:dragon_grumble_1",
        "volume": 1.5,
        "pitch": 1.0
      }
    ]
  },
  "dragon_grumble_2": {
    "subtitle": "Dragon grumbles",
    "sounds": [
      {
        "name": "lightningdragon:dragon_grumble_2",
        "volume": 1.5,
        "pitch": 1.0
      }
    ]
  },
  "dragon_grumble_3": {
    "subtitle": "Dragon grumbles",
    "sounds": [
      {
        "name": "lightningdragon:dragon_grumble_3",
        "volume": 1.5,
        "pitch": 1.0
      }
    ]
  },
  "dragon_purr": {
    "subtitle": "Dragon purrs contentedly",
    "sounds": [
      {
        "name": "lightningdragon:dragon_purr",
        "volume": 0.7,
        "pitch": 1.0
      }
    ]
  },
  "dragon_snort": {
    "subtitle": "Dragon snorts",
    "sounds": [
      {
        "name": "lightningdragon:dragon_snort",
        "volume": 0.9,
        "pitch": 1.0
      }
    ]
  },
  "dragon_chuff": {
    "subtitle": "Dragon chuffs",
    "sounds": [
      {
        "name": "lightningdragon:dragon_chuff",
        "volume": 0.8,
        "pitch": 1.0
      }
    ]
  },
  "dragon_content": {
    "subtitle": "Dragon sounds content",
    "sounds": [
      {
        "name": "lightningdragon:dragon_content",
        "volume": 0.8,
        "pitch": 1.0
      }
    ]
  },
  "dragon_annoyed": {
    "subtitle": "Dragon sounds annoyed",
    "sounds": [
      {
        "name": "lightningdragon:dragon_annoyed",
        "volume": 1.0,
        "pitch": 1.0
      }
    ]
  },
  "dragon_excited": {
    "subtitle": "Dragon sounds excited",
    "sounds": [
      {
        "name": "lightningdragon:dragon_excited",
        "volume": 1.0,
        "pitch": 1.0
      }
    ]
  },
  "dragon_roar_small": {
    "subtitle": "Dragon roars",
    "sounds": [
      {
        "name": "lightningdragon:dragon_roar_small",
        "volume": 1.2,
        "pitch": 1.0
      }
    ]
  },
  "dragon_growl_warning": {
    "subtitle": "Dragon growls menacingly",
    "sounds": [
      {
        "name": "lightningdragon:dragon_growl_warning",
        "volume": 1.1,
        "pitch": 1.0
      }
    ]
  },
  "dragon_step": {
    "subtitle": "Heavy footsteps",
    "sounds": [
      {
        "name": "lightningdragon:dragon_step",
        "volume": 0.6,
        "pitch": 1.0
      }
    ]
  }
}